moia_dev/bastion_host_forward/__init__.py
moia_dev/bastion_host_forward/py.typed
moia_dev/bastion_host_forward/_jsii/__init__.py
moia_dev/bastion_host_forward/_jsii/bastion-host-forward@2.4.2.jsii.tgz
moia_dev_bastion_host_forward-2.4.2.dist-info/LICENSE
moia_dev_bastion_host_forward-2.4.2.dist-info/METADATA
moia_dev_bastion_host_forward-2.4.2.dist-info/WHEEL
moia_dev_bastion_host_forward-2.4.2.dist-info/top_level.txt
moia_dev_bastion_host_forward-2.4.2.dist-info/RECORD
