Metadata-Version: 2.1
Name: moia-dev.bastion-host-forward
Version: 2.4.2
Summary: CDK Construct for creating a bastion host to forward a connection to several AWS data services inside a private subnet from your local machine
Home-page: https://github.com/moia-oss/bastion-host-forward
Author: MOIA GmbH
License: Apache-2.0
Project-URL: Source, https://github.com/moia-oss/bastion-host-forward
Classifier: Intended Audience :: Developers
Classifier: Operating System :: OS Independent
Classifier: Programming Language :: JavaScript
Classifier: Programming Language :: Python :: 3 :: Only
Classifier: Programming Language :: Python :: 3.9
Classifier: Programming Language :: Python :: 3.10
Classifier: Programming Language :: Python :: 3.11
Classifier: Typing :: Typed
Classifier: License :: OSI Approved
Requires-Python: ~=3.9
License-File: LICENSE
Requires-Dist: aws-cdk-lib<3.0.0,>=2.121.1
Requires-Dist: constructs<11.0.0,>=10.3.0
Requires-Dist: jsii<2.0.0,>=1.112.0
Requires-Dist: publication>=0.0.3
Requires-Dist: typeguard<4.3.0,>=2.13.3
